MANIFEST.in
README.md
setup.cfg
setup.py
versioneer.py
voysis/__init__.py
voysis/_version.py
voysis/audio/__init__.py
voysis/audio/audio.py
voysis/audio/keyword_detector.py
voysis/audio/wakeword_detector.py
voysis/client/__init__.py
voysis/client/client.py
voysis/client/client_version_info.py
voysis/client/http_client.py
voysis/client/ws_client.py
voysis/cmd/__init__.py
voysis/cmd/vtc.py
voysis/device/__init__.py
voysis/device/device.py
voysis/device/file_device.py
voysis/device/mic_device.py
voysis_python.egg-info/PKG-INFO
voysis_python.egg-info/SOURCES.txt
voysis_python.egg-info/dependency_links.txt
voysis_python.egg-info/entry_points.txt
voysis_python.egg-info/requires.txt
voysis_python.egg-info/top_level.txt