Metadata-Version: 2.1
Name: voysis-python
Version: 2.0.1
Summary: Voysis Query API Python Library
Home-page: https://github.com/voysis/voysis-python
Author: Voysis
Author-email: support@voysis.com
License: MIT
Platform: UNKNOWN
